ffmenu/__init__.py
ffmenu/apps.py
ffmenu/menu.py
ffmenu/tests.py
ffmenu/templates/ffmenu/menu.html
ffmenu/templatetags/__init__.py
ffmenu/templatetags/menu.py
ffmenu-0.2.1.dist-info/METADATA
ffmenu-0.2.1.dist-info/RECORD
ffmenu-0.2.1.dist-info/WHEEL
ffmenu-0.2.1.dist-info/top_level.txt
