Metadata-Version: 2.1
Name: ffmenu
Version: 0.2.1
Summary: UNKNOWN
Home-page: UNKNOWN
Author: Mārtiņš Šulcs
Author-email: shulcsm@gmail.com
License: UNKNOWN
Platform: UNKNOWN
Requires-Dist: Django (>=1.7)
